sheetsight-0.1.1.dist-info/licenses/LICENSE
sheetsight_py/__init__.py
sheetsight_py/client.py
sheetsight_py/exceptions.py
sheetsight_py/types.py
sheetsight-0.1.1.dist-info/METADATA
sheetsight-0.1.1.dist-info/WHEEL
sheetsight-0.1.1.dist-info/top_level.txt
sheetsight-0.1.1.dist-info/RECORD
