Metadata-Version: 2.4
Name: sheetsight
Version: 0.1.1
Summary: Simple Python client for the Sheetsight Search API
Author: Zach Grimaldi
License-Expression: MIT
Project-URL: Homepage, https://github.com/sheetsight/sheetsight-py
Project-URL: Repository, https://github.com/sheetsight/sheetsight-py.git
Project-URL: Issues, https://github.com/sheetsight/sheetsight-py/issues
Keywords: sheetsight,search,api,client,datasheet,electronics,parts,semiconductor
Classifier: Development Status :: 3 - Alpha
Classifier: Intended Audience :: Developers
Classifier: Programming Language :: Python :: 3
Classifier: Programming Language :: Python :: 3.9
Classifier: Programming Language :: Python :: 3.10
Classifier: Programming Language :: Python :: 3.11
Classifier: Programming Language :: Python :: 3.12
Classifier: Programming Language :: Python :: 3.13
Classifier: Topic :: Software Development :: Libraries :: Python Modules
Classifier: Topic :: Internet :: WWW/HTTP :: HTTP Servers
Classifier: Operating System :: OS Independent
Requires-Python: >=3.9
License-File: LICENSE
Requires-Dist: httpx>=0.25.0
Provides-Extra: dev
Requires-Dist: build>=1.2.2.post1; extra == "dev"
Requires-Dist: pytest>=6.0; extra == "dev"
Requires-Dist: pytest-asyncio>=0.18.0; extra == "dev"
Requires-Dist: pytest-cov>=2.0; extra == "dev"
Requires-Dist: pytest-mock>=3.0; extra == "dev"
Requires-Dist: black>=22.0; extra == "dev"
Requires-Dist: isort>=5.0; extra == "dev"
Requires-Dist: flake8>=4.0; extra == "dev"
Requires-Dist: mypy>=0.950; extra == "dev"
Requires-Dist: python-dotenv>=0.19.0; extra == "dev"
Dynamic: license-file
